onegov.core-0.85.1-py3.6-nspkg.pth
onegov/core/.gitignore
onegov/core/__init__.py
onegov/core/browser_session.py
onegov/core/cache.py
onegov/core/collection.py
onegov/core/converters.py
onegov/core/cronjobs.py
onegov/core/csv.py
onegov/core/datamanager.py
onegov/core/directives.py
onegov/core/elements.py
onegov/core/errors.py
onegov/core/filestorage.py
onegov/core/filters.py
onegov/core/framework.py
onegov/core/html.py
onegov/core/html_diff.py
onegov/core/i18n.py
onegov/core/layout.py
onegov/core/mail.py
onegov/core/markdown.py
onegov/core/metadata.py
onegov/core/redirect.py
onegov/core/request.py
onegov/core/static.py
onegov/core/templates.py
onegov/core/theme.py
onegov/core/upgrade.py
onegov/core/upgrades.py
onegov/core/utils.py
onegov/core/cli/__init__.py
onegov/core/cli/commands.py
onegov/core/cli/core.py
onegov/core/crypto/__init__.py
onegov/core/crypto/password.py
onegov/core/crypto/random.py
onegov/core/crypto/token.py
onegov/core/custom/__init__.py
onegov/core/custom/custom_json.py
onegov/core/orm/__init__.py
onegov/core/orm/cache.py
onegov/core/orm/debug.py
onegov/core/orm/func.py
onegov/core/orm/session_manager.py
onegov/core/orm/sql.py
onegov/core/orm/utils.py
onegov/core/orm/abstract/__init__.py
onegov/core/orm/abstract/adjacency_list.py
onegov/core/orm/abstract/associable.py
onegov/core/orm/mixins/__init__.py
onegov/core/orm/mixins/content.py
onegov/core/orm/mixins/timestamp.py
onegov/core/orm/types/__init__.py
onegov/core/orm/types/hstore_type.py
onegov/core/orm/types/json_type.py
onegov/core/orm/types/lowercase_text_type.py
onegov/core/orm/types/utcdatetime_type.py
onegov/core/orm/types/uuid_type.py
onegov/core/security/__init__.py
onegov/core/security/identity_policy.py
onegov/core/security/permissions.py
onegov/core/security/roles.py
onegov/core/security/rules.py
onegov/core/tests/conftest.py
onegov/core/tests/test_adjacency_list.py
onegov/core/tests/test_browser_session.py
onegov/core/tests/test_cache.py
onegov/core/tests/test_cli.py
onegov.core-0.85.1.dist-info/METADATA
onegov.core-0.85.1.dist-info/WHEEL
onegov.core-0.85.1.dist-info/entry_points.txt
onegov.core-0.85.1.dist-info/namespace_packages.txt
onegov.core-0.85.1.dist-info/top_level.txt
onegov.core-0.85.1.dist-info/RECORD
