Metadata-Version: 2.1
Name: onegov.core
Version: 0.85.1
Summary: Contains code shared by all OneGov applications.
Home-page: http://github.com/onegov/onegov.core
Author: Seantis GmbH
Author-email: info@seantis.ch
License: GPLv2
Platform: any
Classifier: Intended Audience :: Developers
Classifier: Programming Language :: Python :: 3 :: Only
Classifier: Programming Language :: Python :: 3.4
Classifier: Programming Language :: Python :: 3.5
Classifier: Topic :: Software Development :: Libraries :: Python Modules
Classifier: License :: OSI Approved :: GNU General Public License v2 (GPLv2)
Requires-Python: >=3.6
Requires-Dist: alembic
Requires-Dist: arrow
Requires-Dist: babel (>=2.6.0)
Requires-Dist: blinker
Requires-Dist: bcrypt
Requires-Dist: bleach (>=3.0.0)
Requires-Dist: cached-property
Requires-Dist: chameleon (>=3.0.0)
Requires-Dist: click
Requires-Dist: dill (!=0.2.7)
Requires-Dist: dogpile.cache
Requires-Dist: editdistance
Requires-Dist: fastcache
Requires-Dist: fs (>=2.0.0)
Requires-Dist: genshi
Requires-Dist: hiredis
Requires-Dist: html2text
Requires-Dist: html5lib
Requires-Dist: itsdangerous
Requires-Dist: isodate
Requires-Dist: lazy-object-proxy
Requires-Dist: mistletoe
Requires-Dist: mailthon (>=0.1.1)
Requires-Dist: morepath (>=0.18)
Requires-Dist: more.content-security
Requires-Dist: more.transaction (>=0.5)
Requires-Dist: more.webassets (>=0.3.1)
Requires-Dist: onegov.server (>=0.7.0)
Requires-Dist: ordered-set
Requires-Dist: passlib
Requires-Dist: polib
Requires-Dist: psqlparse
Requires-Dist: python-magic (>=0.4.12)
Requires-Dist: psycopg2
Requires-Dist: pycurl
Requires-Dist: pyreact
Requires-Dist: pytz
Requires-Dist: purl
Requires-Dist: redis (!=3.1.0)
Requires-Dist: rcssmin
Requires-Dist: sedate
Requires-Dist: sqlalchemy (>=1.2.4)
Requires-Dist: sqlalchemy-utils
Requires-Dist: sqlparse
Requires-Dist: translationstring
Requires-Dist: toposort
Requires-Dist: unidecode
Requires-Dist: webtest
Requires-Dist: wtforms
Requires-Dist: xlrd
Requires-Dist: xlsxwriter
Requires-Dist: yubico-client
Requires-Dist: zope.sqlalchemy
Provides-Extra: test
Requires-Dist: coverage ; extra == 'test'
Requires-Dist: freezegun ; extra == 'test'
Requires-Dist: onegov-testing ; extra == 'test'
Requires-Dist: openpyxl ; extra == 'test'
Requires-Dist: pyquery ; extra == 'test'
Requires-Dist: pytest-localserver ; extra == 'test'
Requires-Dist: pytest-rerunfailures ; extra == 'test'
Requires-Dist: requests ; extra == 'test'
